frequency_dict/__init__.py
frequency_dict/frequency_dict_from_collection.py
frequency_dict-0.0.1.dist-info/LICENSE
frequency_dict-0.0.1.dist-info/METADATA
frequency_dict-0.0.1.dist-info/WHEEL
frequency_dict-0.0.1.dist-info/top_level.txt
frequency_dict-0.0.1.dist-info/RECORD
